keploy/Keploy.py
keploy/__init__.py
keploy/djangoCov.py
keploy/fastApiCov.py
keploy/flaskCov.py
keploy/utils.py
keploy-2.0.0a39.dist-info/LICENSE
keploy-2.0.0a39.dist-info/METADATA
keploy-2.0.0a39.dist-info/WHEEL
keploy-2.0.0a39.dist-info/top_level.txt
keploy-2.0.0a39.dist-info/RECORD
