Metadata-Version: 2.1
Name: keploy
Version: 2.0.0a39
Summary: Run your unit tests with Keploy
Author: Keploy Inc.
Author-email: hello@keploy.io
Keywords: keploy,python,sdk
Classifier: Development Status :: 3 - Alpha
Classifier: Intended Audience :: Education
Classifier: Programming Language :: Python :: 2
Classifier: Programming Language :: Python :: 3
Classifier: Operating System :: MacOS :: MacOS X
Classifier: Operating System :: Microsoft :: Windows
Classifier: Operating System :: POSIX :: Linux
License-File: LICENSE
